{"ATLAS":{"SPRITES":[
{"SPRITE":{"name":"0","x":1283,"y":610,"w":29,"h":19,"rotated":false}},
{"SPRITE":{"name":"1","x":1337,"y":1856,"w":163,"h":68,"rotated":false}},
{"SPRITE":{"name":"2","x":1338,"y":1784,"w":160,"h":71,"rotated":false}},
{"SPRITE":{"name":"3","x":1156,"y":1910,"w":158,"h":73,"rotated":false}},
{"SPRITE":{"name":"4","x":1315,"y":1925,"w":159,"h":67,"rotated":false}},
{"SPRITE":{"name":"5","x":1181,"y":1752,"w":156,"h":79,"rotated":false}},
{"SPRITE":{"name":"6","x":1181,"y":1832,"w":155,"h":77,"rotated":false}},
{"SPRITE":{"name":"7","x":318,"y":1981,"w":329,"h":57,"rotated":false}},
{"SPRITE":{"name":"8","x":2,"y":1922,"w":315,"h":71,"rotated":false}},
{"SPRITE":{"name":"9","x":2,"y":2,"w":787,"h":957,"rotated":false}},
{"SPRITE":{"name":"10","x":386,"y":1649,"w":280,"h":331,"rotated":false}},
{"SPRITE":{"name":"11","x":790,"y":648,"w":551,"h":493,"rotated":false}},
{"SPRITE":{"name":"12","x":1283,"y":2,"w":517,"h":607,"rotated":false}},
{"SPRITE":{"name":"13","x":790,"y":2,"w":492,"h":645,"rotated":false}},
{"SPRITE":{"name":"14","x":1635,"y":2011,"w":34,"h":35,"rotated":false}},
{"SPRITE":{"name":"15","x":1563,"y":1378,"w":356,"h":272,"rotated":false}},
{"SPRITE":{"name":"16","x":1563,"y":1651,"w":340,"h":281,"rotated":false}},
{"SPRITE":{"name":"17","x":2,"y":1649,"w":383,"h":272,"rotated":false}},
{"SPRITE":{"name":"18","x":1563,"y":1118,"w":401,"h":259,"rotated":false}},
{"SPRITE":{"name":"19","x":1801,"y":2,"w":46,"h":287,"rotated":false}},
{"SPRITE":{"name":"20","x":1027,"y":1554,"w":148,"h":207,"rotated":false}},
{"SPRITE":{"name":"21","x":812,"y":1851,"w":106,"h":186,"rotated":false}},
{"SPRITE":{"name":"22","x":1176,"y":1554,"w":154,"h":197,"rotated":false}},
{"SPRITE":{"name":"23","x":667,"y":1630,"w":359,"h":220,"rotated":false}},
{"SPRITE":{"name":"24","x":1050,"y":1908,"w":105,"h":111,"rotated":false}},
{"SPRITE":{"name":"25","x":1920,"y":1378,"w":123,"h":181,"rotated":false}},
{"SPRITE":{"name":"26","x":919,"y":1851,"w":130,"h":145,"rotated":false}},
{"SPRITE":{"name":"27","x":1920,"y":1560,"w":123,"h":181,"rotated":false}},
{"SPRITE":{"name":"28","x":1050,"y":1762,"w":130,"h":145,"rotated":false}},
{"SPRITE":{"name":"29","x":1904,"y":1742,"w":93,"h":235,"rotated":false}},
{"SPRITE":{"name":"30","x":1393,"y":1118,"w":169,"h":665,"rotated":false}},
{"SPRITE":{"name":"31","x":1852,"y":2,"w":86,"h":912,"rotated":false}},
{"SPRITE":{"name":"32","x":1939,"y":2,"w":53,"h":974,"rotated":false}},
{"SPRITE":{"name":"33","x":1572,"y":1933,"w":62,"h":92,"rotated":false}},
{"SPRITE":{"name":"34","x":1706,"y":1933,"w":69,"h":71,"rotated":false}},
{"SPRITE":{"name":"35","x":1635,"y":1933,"w":70,"h":77,"rotated":false}},
{"SPRITE":{"name":"36","x":546,"y":960,"w":237,"h":178,"rotated":false}},
{"SPRITE":{"name":"37","x":2,"y":1994,"w":93,"h":44,"rotated":false}},
{"SPRITE":{"name":"38","x":667,"y":1851,"w":144,"h":146,"rotated":false}},
{"SPRITE":{"name":"39","x":1852,"y":977,"w":93,"h":83,"rotated":false}},
{"SPRITE":{"name":"40","x":1475,"y":1933,"w":96,"h":76,"rotated":false}},
{"SPRITE":{"name":"41","x":1776,"y":1933,"w":91,"h":50,"rotated":false}},
{"SPRITE":{"name":"42","x":1852,"y":1061,"w":89,"h":56,"rotated":false}},
{"SPRITE":{"name":"43","x":2,"y":960,"w":543,"h":688,"rotated":false}},
{"SPRITE":{"name":"44","x":546,"y":1142,"w":441,"h":487,"rotated":false}},
{"SPRITE":{"name":"45","x":1342,"y":610,"w":509,"h":507,"rotated":false}},
{"SPRITE":{"name":"46","x":988,"y":1142,"w":404,"h":411,"rotated":false}}]},
"meta":{
"app":"Adobe Animate (Better TA Extension)",
"version":"22.0.2.168",
"image":"spritemap1.png",
"format":"RGBA8888",
"size":{"w":2045,"h":2048},
"resolution":"1"
}
}